talentrank/__init__.py
talentrank/main.py
talentrank/data/__init__.py
talentrank/data/business_analyst_target_vector.pkl
talentrank/data/system_design.png
talentrank/data_processor/__init__.py
talentrank/data_processor/job_details_processor.py
talentrank/data_processor/preprocessor.py
talentrank/data_processor/processor.py
talentrank/similarity/__init__.py
talentrank/similarity/similarity_functions.py
talentrank/util/__init__.py
talentrank/util/data_cleaner.py
talentrank/util/util.py
talentrank-1.0.0.dist-info/LICENSE
talentrank-1.0.0.dist-info/METADATA
talentrank-1.0.0.dist-info/WHEEL
talentrank-1.0.0.dist-info/entry_points.txt
talentrank-1.0.0.dist-info/top_level.txt
talentrank-1.0.0.dist-info/RECORD
