Metadata-Version: 2.1
Name: talentrank
Version: 1.0.0
Summary: An advanced information retrieval and recommendation system for ranking job candidates.
Home-page: https://github.com/DavVratChadha/TalentRank
Author: Dav Vrat Chadha
Author-email: davvratchadha1@gmail.com
License: UNKNOWN
Platform: UNKNOWN
Classifier: Programming Language :: Python :: 3
Classifier: License :: OSI Approved :: MIT License
Classifier: Operating System :: OS Independent
Requires-Python: >=3.8
License-File: LICENSE
Requires-Dist: chromadb>=0.5.20
Requires-Dist: pandas>=2.2.3
Requires-Dist: numpy<2.0,>=1.26.4
Requires-Dist: sentence-transformers>=3.3.1
Requires-Dist: openpyxl>=3.1.5
